CHANGES.txt
LICENSE
MANIFEST.in
README.rst
TODO.txt
pyproject.toml
setup.cfg
setup.py
tox.ini
src/pyramid_debugtoolbar_api_sqlalchemy/__init__.py
src/pyramid_debugtoolbar_api_sqlalchemy/panels.py
src/pyramid_debugtoolbar_api_sqlalchemy/utils.py
src/pyramid_debugtoolbar_api_sqlalchemy/views.py
src/pyramid_debugtoolbar_api_sqlalchemy.egg-info/PKG-INFO
src/pyramid_debugtoolbar_api_sqlalchemy.egg-info/SOURCES.txt
src/pyramid_debugtoolbar_api_sqlalchemy.egg-info/dependency_links.txt
src/pyramid_debugtoolbar_api_sqlalchemy.egg-info/not-zip-safe
src/pyramid_debugtoolbar_api_sqlalchemy.egg-info/requires.txt
src/pyramid_debugtoolbar_api_sqlalchemy.egg-info/top_level.txt
src/pyramid_debugtoolbar_api_sqlalchemy/templates/sqlalchemy_csv.dbtmako
tests/test_config.py