Metadata-Version: 2.1
Name: pyramid-debugtoolbar-api-sqlalchemy
Version: 0.3.1
Summary: SQLAlchemy CSV exporting for pyramid_debugtoolbar
Home-page: https://github.com/jvanasco/pyramid_debugtoolbar_api_sqlalchemy
Author: Jonathan Vanasco
Author-email: jonathan@findmeon.com
License: MIT
Keywords: web pyramid sqlalchemy
Platform: UNKNOWN
Classifier: Intended Audience :: Developers
Classifier: Framework :: Pyramid
Classifier: Programming Language :: Python
Classifier: Programming Language :: Python :: 2
Classifier: Programming Language :: Python :: 3
Classifier: License :: OSI Approved :: MIT License
Provides-Extra: testing
